odoo10_addon_account_financial_report_date_range-10.0.1.0.0.99.dev4-py2.7-nspkg.pth
odoo/addons/account_financial_report_date_range/README.rst
odoo/addons/account_financial_report_date_range/__init__.py
odoo/addons/account_financial_report_date_range/__manifest__.py
odoo/addons/account_financial_report_date_range/i18n/account_financial_report_date_range.pot
odoo/addons/account_financial_report_date_range/static/description/icon.png
odoo/addons/account_financial_report_date_range/tests/__init__.py
odoo/addons/account_financial_report_date_range/tests/test_accounting_report.py
odoo/addons/account_financial_report_date_range/wizards/__init__.py
odoo/addons/account_financial_report_date_range/wizards/account_common_report.py
odoo/addons/account_financial_report_date_range/wizards/accounting_report.xml
odoo10_addon_account_financial_report_date_range-10.0.1.0.0.99.dev4.dist-info/DESCRIPTION.rst
odoo10_addon_account_financial_report_date_range-10.0.1.0.0.99.dev4.dist-info/METADATA
odoo10_addon_account_financial_report_date_range-10.0.1.0.0.99.dev4.dist-info/RECORD
odoo10_addon_account_financial_report_date_range-10.0.1.0.0.99.dev4.dist-info/WHEEL
odoo10_addon_account_financial_report_date_range-10.0.1.0.0.99.dev4.dist-info/metadata.json
odoo10_addon_account_financial_report_date_range-10.0.1.0.0.99.dev4.dist-info/namespace_packages.txt
odoo10_addon_account_financial_report_date_range-10.0.1.0.0.99.dev4.dist-info/top_level.txt
