Metadata-Version: 2.0
Name: odoo10-addon-account-financial-report-date-range
Version: 10.0.1.0.0.99.dev4
Summary: Add Date Range field to the Odoo OE standard addons
Home-page: https://github.com/OCA/account-financial-reporting
Author: Noviat,Odoo Community Association (OCA)
Author-email: support@odoo-community.org
License: AGPL-3
Platform: UNKNOWN
Classifier: Programming Language :: Python
Classifier: Framework :: Odoo
Classifier: License :: OSI Approved :: GNU Affero General Public License v3
Requires-Python: ~=2.7
Requires-Dist: odoo (<10.1dev,>=10.0)
Requires-Dist: odoo10-addon-date-range
